__main__.py
api_endpoints_enhanced.py
api_token_manager.py
auth_manager.py
i18n.py
language_manager.py
langwatch_optimizer.py
prompt_builder.py
prompt_data_manager.py
release_api_endpoints.py
release_manager.py
run.py
src/__init__.py
src/auth/__init__.py
src/auth/models/__init__.py
src/auth/models/tenant.py
src/auth/models/user.py
src/auth/security/__init__.py
src/auth/security/password_handler.py
src/core/__init__.py
src/core/base/__init__.py
src/core/base/database_manager.py
src/core/base/repository_base.py
src/core/base/service_base.py
src/core/config/__init__.py
src/core/config/ai_model_config.py
src/core/config/settings.py
src/core/exceptions/__init__.py
src/core/exceptions/base.py
src/core/services/ai_model_manager.py
src/projects/__init__.py
src/projects/models/__init__.py
src/projects/models/project.py
src/projects/repositories/__init__.py
src/projects/repositories/project_repository.py
src/projects/services/__init__.py
src/projects/services/project_service.py
src/prompts/__init__.py
src/prompts/models/__init__.py
src/prompts/models/prompt.py
src/prompts/repositories/__init__.py
src/prompts/repositories/prompt_repository.py
src/prompts/services/__init__.py
src/prompts/services/prompt_service.py
src/prompts/services/template_service.py
src/templates/models/template.py
src/utils/__init__.py
src/utils/github_format.py
src/utils/helpers.py
src/utils/logging_config.py
src/utils/validators.py
text_translator.py
token_calculator.py
web_app.py
promptman-0.6.1.dist-info/LICENSE
promptman-0.6.1.dist-info/METADATA
promptman-0.6.1.dist-info/WHEEL
promptman-0.6.1.dist-info/RECORD
