Metadata-Version: 2.3
Name: promptman
Version: 0.6.1
Summary: Modern AI Prompt Management System with FastAPI Web UI, Dynamic Multi-Language Support, and AI-Powered Optimization
License: Non-Commercial
Author: MakerCorn
Author-email: corn.mendoza@outlook.com
Requires-Python: >=3.12,<4.0
Classifier: License :: Other/Proprietary License
Classifier: Programming Language :: Python :: 3
Classifier: Programming Language :: Python :: 3.12
Classifier: Programming Language :: Python :: 3.13
Provides-Extra: dev
Provides-Extra: password-hashing
Requires-Dist: argon2-cffi (>=25.1.0,<26.0.0) ; extra == "password-hashing"
Requires-Dist: bandit (>=1.8.6,<2.0.0)
Requires-Dist: bcrypt (>=4.0.0,<5.0.0) ; extra == "password-hashing"
Requires-Dist: black (>=25.1.0,<26.0.0) ; extra == "dev"
Requires-Dist: cryptography (>=45.0.5,<46.0.0)
Requires-Dist: fastapi (>=0.116.1,<1.0.0)
Requires-Dist: flake8 (>=7.3.0,<8.0.0) ; extra == "dev"
Requires-Dist: isort (>=6.0.1,<7.0.0)
Requires-Dist: itsdangerous (>=2.1.2,<3.0.0)
Requires-Dist: jinja2 (>=3.1.2,<4.0.0)
Requires-Dist: mypy (>=1.17.0,<2.0.0) ; extra == "dev"
Requires-Dist: psycopg2-binary (>=2.9.10,<3.0.0)
Requires-Dist: pydantic (>=2.11.7,<3.0.0)
Requires-Dist: pyjwt (>=2.10.1,<3.0.0)
Requires-Dist: python-dotenv (>=1.1.0,<2.0.0)
Requires-Dist: python-multipart (>=0.0.6,<1.0.0)
Requires-Dist: requests (>=2.32.4,<3.0.0)
Requires-Dist: starlette (>=0.27.0,<1.0.0)
Requires-Dist: tiktoken (>=0.8.0,<1.0.0)
